README.md
setup.py
MistressGPT.egg-info/PKG-INFO
MistressGPT.egg-info/SOURCES.txt
MistressGPT.egg-info/dependency_links.txt
MistressGPT.egg-info/entry_points.txt
MistressGPT.egg-info/requires.txt
MistressGPT.egg-info/top_level.txt
chatmistress/__init__.py
chatmistress/chatmistress.py
chatmistress/core.py
chatmistress/gui_debug.py
chatmistress/logging_utils.py
chatmistress/utils.py
chatmistress/webbot.py
chatmistress/webbot2.py
chatmistress/assets/Kelpy-Codos.js
chatmistress/assets/custom.css
chatmistress/assets/custom.js
chatmistress/assets/favicon.ico
chatmistress/roles/landlady.yml
chatmistress/roles/wife.yml
chatmistress/templates/role_play_summary.txt
chatmistress/templates/role_play_sys.txt