Metadata-Version: 2.1
Name: MistressGPT
Version: 0.9.9
Summary: MistressGPT: 基于GPT3.5的女王聊天室 👠
